potentiostat/__init__.py
potentiostat/potentiostat.py
potentiostat-0.0.4.dist-info/DESCRIPTION.rst
potentiostat-0.0.4.dist-info/METADATA
potentiostat-0.0.4.dist-info/RECORD
potentiostat-0.0.4.dist-info/WHEEL
potentiostat-0.0.4.dist-info/metadata.json
potentiostat-0.0.4.dist-info/top_level.txt
