Metadata-Version: 2.0
Name: potentiostat
Version: 0.0.4
Summary: This module implements the serial interface to the Rodeostat open source 
Home-page: http://www.aptacam.com/
Author: aptacam
Author-email: UNKNOWN
License: UNKNOWN
Keywords: aptacam
Platform: UNKNOWN
